{
  "resultados": [
    {
      "partido": "PARTIDO LIBERAL DE HONDURAS",
      "candidato": "SALVADOR ALEJANDRO CESAR NASRALLA SALUM",
      "votos": "103",
      "porcentaje": "42.38"
    },
    {
      "partido": "PARTIDO NACIONAL DE HONDURAS",
      "candidato": "NASRY JUAN ASFURA ZABLAH",
      "votos": "91",
      "porcentaje": "37.44"
    },
    {
      "partido": "PARTIDO LIBERTAD Y REFUNDACION",
      "candidato": "RIXI RAMONA MONCADA GODOY",
      "votos": "48",
      "porcentaje": "19.75"
    },
    {
      "partido": "PARTIDO INNOVACION Y UNIDAD SOCIAL DEMOCRATA",
      "candidato": "JORGE NELSON AVILA GUTIERREZ",
      "votos": "1",
      "porcentaje": "0.41"
    },
    {
      "partido": "PARTIDO DEMOCRATA CRISTIANO DE HONDURAS",
      "candidato": "MARIO ENRIQUE RIVERA CALLEJAS",
      "votos": "0",
      "porcentaje": "0.00"
    }
  ],
  "estadisticas": {
    "totalizacion_actas": {
      "actas_totales": "1",
      "actas_divulgadas": "1"
    },
    "distribucion_votos": {
      "validos": "243",
      "nulos": "4",
      "blancos": "0"
    },
    "estado_actas_divulgadas": {
      "actas_correctas": "1",
      "actas_inconsistentes": "0"
    }
  }
}