{
  "resultados": [
    {
      "partido": "PARTIDO LIBERAL DE HONDURAS",
      "votos": "2,088",
      "porcentaje": "58.34"
    },
    {
      "partido": "PARTIDO LIBERTAD Y REFUNDACION",
      "votos": "646",
      "porcentaje": "18.04"
    },
    {
      "partido": "PARTIDO NACIONAL DE HONDURAS",
      "votos": "517",
      "porcentaje": "14.44"
    },
    {
      "partido": "PARTIDO INNOVACION Y UNIDAD SOCIAL DEMOCRATA",
      "votos": "179",
      "porcentaje": "5.00"
    },
    {
      "partido": "PARTIDO DEMOCRATA CRISTIANO DE HONDURAS",
      "votos": "149",
      "porcentaje": "4.16"
    }
  ],
  "estadisticas": {
    "totalizacion_actas": {
      "actas_totales": "1",
      "actas_divulgadas": "1"
    },
    "distribucion_votos": {
      "validos": "3,579",
      "nulos": "5",
      "blancos": "10"
    },
    "estado_actas_divulgadas": {
      "actas_correctas": "1",
      "actas_inconsistentes": "0"
    }
  }
}