{
  "resultados": [
    {
      "partido": "PARTIDO LIBERTAD Y REFUNDACION",
      "candidato": "PARTIDO LIBERTAD Y REFUNDACION ",
      "votos": "110",
      "porcentaje": "47.00"
    },
    {
      "partido": "PARTIDO NACIONAL DE HONDURAS",
      "candidato": "PARTIDO NACIONAL DE HONDURAS ",
      "votos": "71",
      "porcentaje": "30.34"
    },
    {
      "partido": "PARTIDO LIBERAL DE HONDURAS",
      "candidato": "PARTIDO LIBERAL DE HONDURAS ",
      "votos": "41",
      "porcentaje": "17.52"
    },
    {
      "partido": "PARTIDO DEMOCRATA CRISTIANO DE HONDURAS",
      "candidato": "PARTIDO DEMOCRATA CRISTIANO DE HONDURAS ",
      "votos": "7",
      "porcentaje": "2.99"
    },
    {
      "partido": "PARTIDO INNOVACION Y UNIDAD SOCIAL DEMOCRATA",
      "candidato": "PARTIDO INNOVACION Y UNIDAD SOCIAL DEMOCRATA ",
      "votos": "5",
      "porcentaje": "2.13"
    }
  ],
  "estadisticas": {
    "totalizacion_actas": {
      "actas_totales": "1",
      "actas_divulgadas": "1"
    },
    "distribucion_votos": {
      "validos": "234",
      "nulos": "3",
      "blancos": "2"
    },
    "estado_actas_divulgadas": {
      "actas_correctas": "1",
      "actas_inconsistentes": "0"
    }
  }
}